{"boxes": [{"position": [0, 295, 76], "size": [295, 295, 75], "color": [252, 33, 43]}, {"position": [0, 0, 150], "size": [295, 295, 70], "color": [55, 55, 173]}, {"position": [0, 0, 75], "size": [295, 295, 75], "color": [145, 136, 106]}, {"position": [0, 295, 1], "size": [295, 295, 75], "color": [162, 115, 168]}, {"position": [0, 295, 151], "size": [295, 295, 50], "color": [90, 94, 226]}, {"position": [0, 295, 276], "size": [295, 295, 45], "color": [6, 82, 57]}, {"position": [0, 295, 201], "size": [295, 295, 75], "color": [8, 1, 115]}, {"position": [0, 0, 0], "size": [295, 295, 75], "color": [189, 42, 36]}, {"position": [0, 0, 220], "size": [295, 295, 68], "color": [197, 53, 28]}, {"position": [0, 0, 288], "size": [295, 295, 35], "color": [26, 46, 233]}], "text": "Solution"}